<?xml version="1.0" encoding="utf-8" ?><dwsync><file name="swimming.html" server="geometrixx.businesscatalyst.com" local="3595258649" remote="3595260985" Dst="-1" /><file name="biking.html" server="geometrixx.businesscatalyst.com" local="3595258649" remote="3595261054" Dst="-1" /><file name="sunglasses.html" server="geometrixx.businesscatalyst.com" local="3595258649" remote="3595261106" Dst="-1" /><file name="hiking.html" server="geometrixx.businesscatalyst.com" local="3595258649" remote="3595261106" Dst="-1" /><file name="skiing.html" server="geometrixx.businesscatalyst.com" local="3595258649" remote="3595261107" Dst="-1" /><file name="surfing.html" server="geometrixx.businesscatalyst.com" local="3595258649" remote="3595261107" Dst="-1" /><file name="running.html" server="geometrixx.businesscatalyst.com" local="3595258649" remote="3595261108" Dst="-1" /><file name="swimming.html" server="geometrixx.businesscatalyst.com/geometrixx/" local="3595945869" remote="3595946401" Dst="-1" /><file name="biking.html" server="geometrixx.businesscatalyst.com/geometrixx/" local="3595945869" remote="3595946452" Dst="-1" /><file name="sunglasses.html" server="geometrixx.businesscatalyst.com/geometrixx/" local="3595945869" remote="3595946490" Dst="-1" /><file name="hiking.html" server="geometrixx.businesscatalyst.com/geometrixx/" local="3595945869" remote="3595946490" Dst="-1" /><file name="skiing.html" server="geometrixx.businesscatalyst.com/geometrixx/" local="3595945869" remote="3595946491" Dst="-1" /><file name="surfing.html" server="geometrixx.businesscatalyst.com/geometrixx/" local="3595945869" remote="3595946492" Dst="-1" /><file name="running.html" server="geometrixx.businesscatalyst.com/geometrixx/" local="3595945869" remote="3595946492" Dst="-1" /><file name=".DS_Store" server="geooutdoors02.worldsecuresystems.com/geometrixx/" local="3603311622" remote="3604940637" Dst="-1" /><file name="biking.html" server="geooutdoors02.worldsecuresystems.com/geometrixx/" local="3605032871" remote="3605037749" Dst="-1" /><file name="hiking.html" server="geooutdoors02.worldsecuresystems.com/geometrixx/" local="3605032871" remote="3605037753" Dst="-1" /><file name="running.html" server="geooutdoors02.worldsecuresystems.com/geometrixx/" local="3605032871" remote="3605037756" Dst="-1" /><file name="skiing.html" server="geooutdoors02.worldsecuresystems.com/geometrixx/" local="3605032871" remote="3605037765" Dst="-1" /><file name="sunglasses.html" server="geooutdoors02.worldsecuresystems.com/geometrixx/" local="3605032871" remote="3605037767" Dst="-1" /><file name="surfing.html" server="geooutdoors02.worldsecuresystems.com/geometrixx/" local="3605032871" remote="3605037768" Dst="-1" /><file name="swimming.html" server="geooutdoors02.worldsecuresystems.com/geometrixx/" local="3605032871" remote="3605037770" Dst="-1" /></dwsync>